{
  "meta": {
    "last_rss_poll": "2026-06-15T01:28Z",
    "source": "R2 live via monitor-ingest rss_news (post 27518656143, 27518740552)",
    "total_items": 8,
    "note": "Sample data synthesized from RSS ingest (e.g. justice-pr), border-funding-synthesis.json, and cross-arena ripples. In live: fetch https://<public-r2>/processed/news/news-index.json or individual RSS processed items. Pipeline: monitor_and_ingest.py -> raw/news/rss-*.json -> process_data.py -> signals in processed.",
    "R2_VERIFIER_note": "R2 VERIFIER: new hits confirmed post 27518656739 | raw/news/ paths live | MCP + test-r2 green. Chain to process/analyze for news_ripples.",
    "recent_paths": [
      "raw/news/rss-whitehouse-20260615-0126-*.html (multiple, 50kB+, R2 Verified)",
      "raw/news/rss-justice-pr-20260615-0126-*.html (PR statements, ~1.5kB, R2 Verified)",
      "raw/media/rss-*.xml (feed snapshots)"
    ],
    "liveness": {
      "whitehouse": 30,
      "justice": 25,
      "Xapprox62": 62,
      "total_recent_ingest": "~10+"
    },
    "processed_note": "processed/news/ expected post auto chain (process_data supports rss/news)",
    "MCP_buckets": "babylon-raw-data + 6 siblings (ENAM Standard)",
    "updated_by": "R2 CF NEWS VERIFIER + ACTIVATOR SUBAGENT"
  },
  "newsItems": [
    {
      "id": "rss-whitehouse-20260615-0126-presidential-actions-homeownership",
      "title": "Presidential Actions 2026-06 National Homeownership Month 2026",
      "source": "whitehouse",
      "pubDate": "2026-06-15T01:26Z",
      "excerpt": "From live RSS ingest to raw/news/ ... (full HTML in R2 babylon-raw-data)",
      "link": "https://www.whitehouse.gov/ (presidential-actions)",
      "arena": "news",
      "r2_path": "raw/news/rss-whitehouse-20260615-0126-presidential-actions-2026-06-national-homeownership-month-2026.html",
      "r2_verified": true,
      "signals": {
        "framingScore": 0.6,
        "tags": [
          "presidential",
          "liveness",
          "rss"
        ],
        "source": "whitehouse-rss"
      }
    },
    {
      "id": "rss-justice-001",
      "title": "Coordinated Law Enforcement Actions Results in Arrests of Seven Men in Connection with Fraudulent COVID-19 Relief Loan Applications",
      "source": "justice-pr",
      "pubDate": "2026-06-12T12:00:00Z",
      "excerpt": "LAS VEGAS – As a result of coordinated law enforcement actions in three states, seven men have been arrested and indicted in connection with submitting fraudulent COVID-19 relief loan applications...",
      "link": "https://www.justice.gov/usao-nv/pr/coordinated-law-enforcement-actions-results-arrests-seven-men-connection-fraudulent",
      "arena": "news",
      "signals": {
        "framingScore": 0.68,
        "repeatedPhrases": ["coordinated law enforcement actions"],
        "tags": ["coordination", "fraud", "arrests"],
        "loadedLanguage": 0.42
      }
    }
  ],
  "politicians": [],
  "synthesis": {}
}