{"httpProtocol":"HTTP/2","clientAcceptEncoding":"gzip, deflate, br","requestPriority":"weight=16;exclusive=0;group=0;group-weight=0","edgeRequestKeepAliveStatus":1,"requestHeaderNames":{},"clientTcpRtt":16,"clientQuicRtt":0,"colo":"CLE","asn":10796,"asOrganization":"Charter Communications Inc","country":"US","isEUCountry":false,"city":"Springboro","continent":"NA","region":"Ohio","regionCode":"OH","timezone":"America/New_York","longitude":"-84.23327","latitude":"39.55228","postalCode":"45066","metroCode":"515","tlsVersion":"TLSv1.3","tlsCipher":"AEAD-AES256-GCM-SHA384","tlsClientRandom":"RiU7TGhUy+u1LGGlo6nh6/nKMm1W22BKSKJaMM86gbU=","tlsClientCiphersSha1":"kXrN3VEKDdzz2cPKTQaKzpxVTxQ=","tlsClientExtensionsSha1":"1eY97BUYYO8vDaTfHQywB1pcNdM=","tlsClientExtensionsSha1Le":"u4wtEMFQBY18l3BzHAvORm+KGRw=","tlsExportedAuthenticator":{"clientHandshake":"75fec17e7d86f9e6b838d61943cfd12abfef087a1c44d73c18084d9638c7b878c71e567b1749822bc94b2e4a71fd1492","serverHandshake":"90c12d2151a2a26d887afa6cac5c607ad7cd8d8ab5dddb5dbbd9892e2791ba4cb32e48ea9c100817665ca11f1e325bf9","clientFinished":"ba8726df76bd5c98f69932ae5f7c0289b9cfd19a34c2d06fefaf43b9f2f87a48e15d4b9e97e4266b510c5d5911889fd9","serverFinished":"3e5239dc093053484e71328d82f4da259d01609b1f033ca679886b3fc4add4b31eea99a1bfe5c151ca41165cde872648"},"tlsClientHelloLength":"1606","tlsClientAuth":{"certPresented":"0","certVerified":"NONE","certRevoked":"0","certIssuerDN":"","certSubjectDN":"","certIssuerDNRFC2253":"","certSubjectDNRFC2253":"","certIssuerDNLegacy":"","certSubjectDNLegacy":"","certSerial":"","certIssuerSerial":"","certSKI":"","certIssuerSKI":"","certFingerprintSHA1":"","certFingerprintSHA256":"","certNotBefore":"","certNotAfter":"","certRFC9440":"","certRFC9440TooLarge":false,"certChainRFC9440":"","certChainRFC9440TooLarge":false},"verifiedBotCategory":"","edgeL4":{"deliveryRate":99851},"botManagement":{"corporateProxy":false,"verifiedBot":false,"jsDetection":{"passed":false},"staticResource":false,"detectionIds":{},"score":99}}